samma1570/__init__.py
samma1570/api/__init__.py
samma1570/api/googleTran.py
samma1570/fileSystem/__init__.py
samma1570/fileSystem/writeJson.py
samma1570/fileSystem/writeJsontoExcel.py
samma1570/mydecorate/__init__.py
samma1570/mydecorate/clockdeco.py
samma1570/mydecorate/debugdeco.py
samma1570/mydecorate/fileiterdeco.py
samma1570/spiderTool/__init__.py
samma1570/spiderTool/myRequest.py
samma1570/spiderTool/output.py
samma1570-1.3.dist-info/METADATA
samma1570-1.3.dist-info/RECORD
samma1570-1.3.dist-info/WHEEL
samma1570-1.3.dist-info/top_level.txt
